{
  "schema_version": "statement_record.v1",
  "case_id": "C-2026-RF000805-乾-甲申丙寅辛酉丙申",
  "generated_at": "2026-06-12T15:52:19Z",
  "source": "P5-7 historical statement record migration",
  "source_rule_version": "phase-300-voting-strategy",
  "records": [
    {
      "statement_id": "S-RF000805-893d68",
      "case_id": "C-2026-RF000805-乾-甲申丙寅辛酉丙申",
      "rule_id": "UNMAPPED",
      "family_id": "UNMAPPED",
      "school": "UNMAPPED",
      "canon": "UNMAPPED",
      "rule_type": "UNMAPPED",
      "statement_text": "2013：凶,学习奥数，觉得很难，受挫",
      "confidence_snapshot": {
        "star": 0,
        "percent": 0.0,
        "posterior_mean": null,
        "sample_n": 0,
        "source": "fallback_initial"
      },
      "generated_at": "2026-06-12T15:52:19Z",
      "source_engine_version": "1.3.1",
      "source_rule_version": "phase-300-voting-strategy",
      "domain": "其他",
      "section": "known_facts_migrated",
      "year": null,
      "needs_mapping_repair": true,
      "mapping_repair_reason": "no_rule_id_in_statement_index"
    },
    {
      "statement_id": "S-RF000805-852f69",
      "case_id": "C-2026-RF000805-乾-甲申丙寅辛酉丙申",
      "rule_id": "UNMAPPED",
      "family_id": "UNMAPPED",
      "school": "UNMAPPED",
      "canon": "UNMAPPED",
      "rule_type": "UNMAPPED",
      "statement_text": "2014：凶,同",
      "confidence_snapshot": {
        "star": 0,
        "percent": 0.0,
        "posterior_mean": null,
        "sample_n": 0,
        "source": "fallback_initial"
      },
      "generated_at": "2026-06-12T15:52:19Z",
      "source_engine_version": "1.3.1",
      "source_rule_version": "phase-300-voting-strategy",
      "domain": "其他",
      "section": "known_facts_migrated",
      "year": null,
      "needs_mapping_repair": true,
      "mapping_repair_reason": "no_rule_id_in_statement_index"
    },
    {
      "statement_id": "S-RF000805-044af1",
      "case_id": "C-2026-RF000805-乾-甲申丙寅辛酉丙申",
      "rule_id": "UNMAPPED",
      "family_id": "UNMAPPED",
      "school": "UNMAPPED",
      "canon": "UNMAPPED",
      "rule_type": "UNMAPPED",
      "statement_text": "2013：课外压力很大，成绩不理想",
      "confidence_snapshot": {
        "star": 0,
        "percent": 0.0,
        "posterior_mean": null,
        "sample_n": 0,
        "source": "fallback_initial"
      },
      "generated_at": "2026-06-12T15:52:19Z",
      "source_engine_version": "1.3.1",
      "source_rule_version": "phase-300-voting-strategy",
      "domain": "其他",
      "section": "known_facts_migrated",
      "year": null,
      "needs_mapping_repair": true,
      "mapping_repair_reason": "no_rule_id_in_statement_index"
    },
    {
      "statement_id": "S-RF000805-3f3761",
      "case_id": "C-2026-RF000805-乾-甲申丙寅辛酉丙申",
      "rule_id": "UNMAPPED",
      "family_id": "UNMAPPED",
      "school": "UNMAPPED",
      "canon": "UNMAPPED",
      "rule_type": "UNMAPPED",
      "statement_text": "2015：吉,获得很多竞赛**，同时被多所市重点中学点招",
      "confidence_snapshot": {
        "star": 0,
        "percent": 0.0,
        "posterior_mean": null,
        "sample_n": 0,
        "source": "fallback_initial"
      },
      "generated_at": "2026-06-12T15:52:19Z",
      "source_engine_version": "1.3.1",
      "source_rule_version": "phase-300-voting-strategy",
      "domain": "其他",
      "section": "known_facts_migrated",
      "year": null,
      "needs_mapping_repair": true,
      "mapping_repair_reason": "no_rule_id_in_statement_index"
    },
    {
      "statement_id": "S-RF000805-929f93",
      "case_id": "C-2026-RF000805-乾-甲申丙寅辛酉丙申",
      "rule_id": "UNMAPPED",
      "family_id": "UNMAPPED",
      "school": "UNMAPPED",
      "canon": "UNMAPPED",
      "rule_type": "UNMAPPED",
      "statement_text": "2016：吉,进入中学后，成绩排名前十，成绩优异",
      "confidence_snapshot": {
        "star": 0,
        "percent": 0.0,
        "posterior_mean": null,
        "sample_n": 0,
        "source": "fallback_initial"
      },
      "generated_at": "2026-06-12T15:52:19Z",
      "source_engine_version": "1.3.1",
      "source_rule_version": "phase-300-voting-strategy",
      "domain": "其他",
      "section": "known_facts_migrated",
      "year": null,
      "needs_mapping_repair": true,
      "mapping_repair_reason": "no_rule_id_in_statement_index"
    },
    {
      "statement_id": "S-RF000805-6f8a4f",
      "case_id": "C-2026-RF000805-乾-甲申丙寅辛酉丙申",
      "rule_id": "UNMAPPED",
      "family_id": "UNMAPPED",
      "school": "UNMAPPED",
      "canon": "UNMAPPED",
      "rule_type": "UNMAPPED",
      "statement_text": "2019：凶,成绩不再如前，排名掉到年纪几十名开外，压力大",
      "confidence_snapshot": {
        "star": 0,
        "percent": 0.0,
        "posterior_mean": null,
        "sample_n": 0,
        "source": "fallback_initial"
      },
      "generated_at": "2026-06-12T15:52:19Z",
      "source_engine_version": "1.3.1",
      "source_rule_version": "phase-300-voting-strategy",
      "domain": "其他",
      "section": "known_facts_migrated",
      "year": null,
      "needs_mapping_repair": true,
      "mapping_repair_reason": "no_rule_id_in_statement_index"
    },
    {
      "statement_id": "S-RF000805-5c83dd",
      "case_id": "C-2026-RF000805-乾-甲申丙寅辛酉丙申",
      "rule_id": "UNMAPPED",
      "family_id": "UNMAPPED",
      "school": "UNMAPPED",
      "canon": "UNMAPPED",
      "rule_type": "UNMAPPED",
      "statement_text": "2021：凶,直到",
      "confidence_snapshot": {
        "star": 0,
        "percent": 0.0,
        "posterior_mean": null,
        "sample_n": 0,
        "source": "fallback_initial"
      },
      "generated_at": "2026-06-12T15:52:19Z",
      "source_engine_version": "1.3.1",
      "source_rule_version": "phase-300-voting-strategy",
      "domain": "其他",
      "section": "known_facts_migrated",
      "year": null,
      "needs_mapping_repair": true,
      "mapping_repair_reason": "no_rule_id_in_statement_index"
    },
    {
      "statement_id": "S-RF000805-b7fb14",
      "case_id": "C-2026-RF000805-乾-甲申丙寅辛酉丙申",
      "rule_id": "UNMAPPED",
      "family_id": "UNMAPPED",
      "school": "UNMAPPED",
      "canon": "UNMAPPED",
      "rule_type": "UNMAPPED",
      "statement_text": "2021：成绩一直如此，不够理想，压力大，迷茫",
      "confidence_snapshot": {
        "star": 0,
        "percent": 0.0,
        "posterior_mean": null,
        "sample_n": 0,
        "source": "fallback_initial"
      },
      "generated_at": "2026-06-12T15:52:19Z",
      "source_engine_version": "1.3.1",
      "source_rule_version": "phase-300-voting-strategy",
      "domain": "其他",
      "section": "known_facts_migrated",
      "year": null,
      "needs_mapping_repair": true,
      "mapping_repair_reason": "no_rule_id_in_statement_index"
    },
    {
      "statement_id": "S-RF000805-8435b7",
      "case_id": "C-2026-RF000805-乾-甲申丙寅辛酉丙申",
      "rule_id": "UNMAPPED",
      "family_id": "UNMAPPED",
      "school": "UNMAPPED",
      "canon": "UNMAPPED",
      "rule_type": "UNMAPPED",
      "statement_text": "2022：吉,吉多于凶，虽备考高考压力大，但成功考入 top2，并进入实验班，成绩专业第一",
      "confidence_snapshot": {
        "star": 0,
        "percent": 0.0,
        "posterior_mean": null,
        "sample_n": 0,
        "source": "fallback_initial"
      },
      "generated_at": "2026-06-12T15:52:19Z",
      "source_engine_version": "1.3.1",
      "source_rule_version": "phase-300-voting-strategy",
      "domain": "其他",
      "section": "known_facts_migrated",
      "year": null,
      "needs_mapping_repair": true,
      "mapping_repair_reason": "no_rule_id_in_statement_index"
    },
    {
      "statement_id": "S-RF000805-80f832",
      "case_id": "C-2026-RF000805-乾-甲申丙寅辛酉丙申",
      "rule_id": "UNMAPPED",
      "family_id": "UNMAPPED",
      "school": "UNMAPPED",
      "canon": "UNMAPPED",
      "rule_type": "UNMAPPED",
      "statement_text": "2023：吉,保持成绩与排名，获得多项**，人际关系好",
      "confidence_snapshot": {
        "star": 0,
        "percent": 0.0,
        "posterior_mean": null,
        "sample_n": 0,
        "source": "fallback_initial"
      },
      "generated_at": "2026-06-12T15:52:19Z",
      "source_engine_version": "1.3.1",
      "source_rule_version": "phase-300-voting-strategy",
      "domain": "其他",
      "section": "known_facts_migrated",
      "year": null,
      "needs_mapping_repair": true,
      "mapping_repair_reason": "no_rule_id_in_statement_index"
    },
    {
      "statement_id": "S-RF000805-66a9de",
      "case_id": "C-2026-RF000805-乾-甲申丙寅辛酉丙申",
      "rule_id": "UNMAPPED",
      "family_id": "UNMAPPED",
      "school": "UNMAPPED",
      "canon": "UNMAPPED",
      "rule_type": "UNMAPPED",
      "statement_text": "2024：吉,保持成绩排名，同时获得国家奖学金，自身能力也有较大提高其他信息: 职业：学生；出身一般中产家庭；健康良好，精力充沛；很有抱负，意志坚定，外向开朗，控制欲强，但性格较急躁，有时过分理性而情感淡薄",
      "confidence_snapshot": {
        "star": 0,
        "percent": 0.0,
        "posterior_mean": null,
        "sample_n": 0,
        "source": "fallback_initial"
      },
      "generated_at": "2026-06-12T15:52:19Z",
      "source_engine_version": "1.3.1",
      "source_rule_version": "phase-300-voting-strategy",
      "domain": "事业",
      "section": "known_facts_migrated",
      "year": null,
      "needs_mapping_repair": true,
      "mapping_repair_reason": "no_rule_id_in_statement_index"
    }
  ]
}
