{
  "case_id": "C-2026-RF000118-乾-己巳癸酉辛丑己丑",
  "generated_at": "2026-06-08",
  "statements": [
    {
      "statement_id": "S-RF000118-ccf625",
      "domain": "其他",
      "summary": "2002：吉,小学很顺利，成绩前列，性格调皮捣蛋。上了市内比较好了初中",
      "status": "observed_fact",
      "section": "known_facts_migrated",
      "rule_ids": [],
      "schools": [],
      "source_raw_id": "RF-2026-000118"
    },
    {
      "statement_id": "S-RF000118-15e222",
      "domain": "健康",
      "summary": "2003：凶,双膝髌骨粉碎性骨折，动手术打了钢板和钢钉在膝盖",
      "status": "observed_fact",
      "section": "known_facts_migrated",
      "rule_ids": [],
      "schools": [],
      "source_raw_id": "RF-2026-000118"
    },
    {
      "statement_id": "S-RF000118-127725",
      "domain": "其他",
      "summary": "2005：吉,初中一直成绩不错，中考记得是全市 100 多名，上了市重点高中，没去，上了省最好的高中",
      "status": "observed_fact",
      "section": "known_facts_migrated",
      "rule_ids": [],
      "schools": [],
      "source_raw_id": "RF-2026-000118"
    },
    {
      "statement_id": "S-RF000118-5d7a0d",
      "domain": "其他",
      "summary": "2008：凶,高考发挥不尽如人意，只考上了 211，大学放飞自我，逃课打游戏",
      "status": "observed_fact",
      "section": "known_facts_migrated",
      "rule_ids": [],
      "schools": [],
      "source_raw_id": "RF-2026-000118"
    },
    {
      "statement_id": "S-RF000118-af9722",
      "domain": "事业",
      "summary": "2013：凶,大学毕业后一年多没找工作，想考研，没忍住还在玩游戏，考研失败",
      "status": "observed_fact",
      "section": "known_facts_migrated",
      "rule_ids": [],
      "schools": [],
      "source_raw_id": "RF-2026-000118"
    },
    {
      "statement_id": "S-RF000118-f35acc",
      "domain": "其他",
      "summary": "2014：吉,把握了一个机会，入行 IT，并且努力钻研技术，通过跳槽提高待遇，税前年薪 5 万",
      "status": "observed_fact",
      "section": "known_facts_migrated",
      "rule_ids": [],
      "schools": [],
      "source_raw_id": "RF-2026-000118"
    },
    {
      "statement_id": "S-RF000118-514fef",
      "domain": "事业",
      "summary": "2015：吉,把握了一个进入银行软件开发中心的机会，成功进入，行内编制，待遇提升，稳定。税前年薪 13 万左右",
      "status": "observed_fact",
      "section": "known_facts_migrated",
      "rule_ids": [],
      "schools": [],
      "source_raw_id": "RF-2026-000118"
    },
    {
      "statement_id": "S-RF000118-3edd20",
      "domain": "财运",
      "summary": "2016：吉,买了房，女朋友也跳槽来到我的城市。税前年薪 15 万左右",
      "status": "observed_fact",
      "section": "known_facts_migrated",
      "rule_ids": [],
      "schools": [],
      "source_raw_id": "RF-2026-000118"
    },
    {
      "statement_id": "S-RF000118-296e34",
      "domain": "财运",
      "summary": "2018：凶,虽然安稳，心里一直不甘于打工，一次行内职级晋升失败，决定跳槽，去了深圳一家外企。深圳工资提高，但是花销也很大，没存什么钱。税前年薪 25 万左右",
      "status": "observed_fact",
      "section": "known_facts_migrated",
      "rule_ids": [],
      "schools": [],
      "source_raw_id": "RF-2026-000118"
    },
    {
      "statement_id": "S-RF000118-5915ff",
      "domain": "事业",
      "summary": "2019：凶,10 月，谋划很久，工作之余，创业。12 月创业刚刚有点起色，碰到疫情，结束创业，亏钱。期间工作没怎么受影响。税前年薪 25 万左右",
      "status": "observed_fact",
      "section": "known_facts_migrated",
      "rule_ids": [],
      "schools": [],
      "source_raw_id": "RF-2026-000118"
    },
    {
      "statement_id": "S-RF000118-6a313e",
      "domain": "财运",
      "summary": "2020：吉,1 月到 3 月一直居家办公，外企虽然也安逸，但是闲不住想挑战，4 月跳槽到华为，工资大幅度提升，但是非常卷和累。税前年薪 45 万左右",
      "status": "observed_fact",
      "section": "known_facts_migrated",
      "rule_ids": [],
      "schools": [],
      "source_raw_id": "RF-2026-000118"
    },
    {
      "statement_id": "S-RF000118-e3366f",
      "domain": "事业",
      "summary": "2021：吉,由于老美持续的制裁华为，算是我战略预判错误，跳槽到央企华润集团，工资降，但是安逸。税前年薪 35 万左右。认得一帮玩德州**的朋友，里面有个很有实力的朋友，挺不错，开始接触股票，一开始就是听他们消息，小赚钱",
      "status": "observed_fact",
      "section": "known_facts_migrated",
      "rule_ids": [],
      "schools": [],
      "source_raw_id": "RF-2026-000118"
    },
    {
      "statement_id": "S-RF000118-259703",
      "domain": "事业",
      "summary": "2022：吉,股票方面，不甘心只听消息，开始自己研究，小亏工作平稳一胎男孩出生，和老婆异地比较痛苦",
      "status": "observed_fact",
      "section": "known_facts_migrated",
      "rule_ids": [],
      "schools": [],
      "source_raw_id": "RF-2026-000118"
    },
    {
      "statement_id": "S-RF000118-4bae83",
      "domain": "财运",
      "summary": "2023：吉,跳槽回珠海，结束异地，老婆很开心工资待遇降低，清闲，税前年薪 30 万左右。摸鱼炒股，小亏",
      "status": "observed_fact",
      "section": "known_facts_migrated",
      "rule_ids": [],
      "schools": [],
      "source_raw_id": "RF-2026-000118"
    }
  ]
}
