{
  "case_id": "C-2026-025-坤-辛未乙未甲辰乙亥",
  "generated_at": "2026-05-31",
  "purpose": "statement-level feedback fanout to rule-level calibration; preserves statement_index.json stable list schema",
  "statements": {
    "S-025-d1a001": {
      "domain": "事业/财富",
      "rule_ids": ["M1-D-013", "M1-D-122", "M2-Y-021"],
      "section": "Step 1/五维定位·事业财富"
    },
    "S-025-d2b001": {
      "domain": "婚恋",
      "rule_ids": ["M2-Y-038"],
      "section": "Step 1/五维定位·婚恋"
    },
    "S-025-hl001": {
      "domain": "学习/旁证",
      "rule_ids": ["M2-Y-021"],
      "section": "Step 1/五维定位·学业旁证"
    },
    "S-025-cns001": {
      "domain": "财富",
      "rule_ids": ["M1-D-013", "M2-Y-021"],
      "section": "Step 2/五维定位·财富"
    },
    "S-025-hl002": {
      "domain": "健康",
      "rule_ids": [],
      "section": "Step 6·健康风险"
    },
    "S-025-yq2018": {
      "domain": "应期",
      "rule_ids": [],
      "section": "Step 7·应期总表",
      "year": 2018
    },
    "S-025-yq2024": {
      "domain": "应期",
      "rule_ids": [],
      "section": "Step 7·应期总表",
      "year": 2024
    },
    "S-025-yq2025": {
      "domain": "应期",
      "rule_ids": [],
      "section": "Step 7·应期总表",
      "year": 2025
    },
    "S-025-yq2027": {
      "domain": "应期",
      "rule_ids": [],
      "section": "Step 7·应期总表",
      "year": 2027
    },
    "S-025-yq2029": {
      "domain": "应期",
      "rule_ids": [],
      "section": "Step 7·应期总表",
      "year": 2029
    }
  }
}
